{"name": "Sauvignon Blanc", "data": [{"name": "acidity", "color": "#F1E3A4", "value": 362.71885263502446}, {"name": "citrus", "color": "#F1E3A4", "value": 349.3979424698638}, {"name": "fruit", "color": "#F1E3A4", "value": 368.9276371253855}, {"name": "green", "color": "#F1E3A4", "value": 377.1945379250677}, {"name": "aromas", "color": "#F1E3A4", "value": 381.69831139227085}, {"name": "palate", "color": "#F1E3A4", "value": 384.0562760182933}, {"name": "lime", "color": "#F1E3A4", "value": 287.5041822670852}, {"name": "crisp", "color": "#F1E3A4", "value": 387.7261413806482}, {"name": "grapefruit", "color": "#F1E3A4", "value": 368.01632142538546}, {"name": "finish", "color": "#F1E3A4", "value": 387.1352323723526}]}